cf_pandas/__init__.py
cf_pandas/_version.py
cf_pandas/accessor.py
cf_pandas/criteria.py
cf_pandas/options.py
cf_pandas/reg.py
cf_pandas/utils.py
cf_pandas/vocab.py
cf_pandas/widget.py
cf_pandas-0.8.1.dist-info/LICENSE.txt
cf_pandas-0.8.1.dist-info/METADATA
cf_pandas-0.8.1.dist-info/WHEEL
cf_pandas-0.8.1.dist-info/top_level.txt
cf_pandas-0.8.1.dist-info/RECORD
