Metadata-Version: 2.1
Name: cf-pandas
Version: 0.8.1
Summary: an accessor for pandas objects that interprets CF attributes
Home-page: https://github.com/axiom-data-science/cf-pandas
Author: Axiom Data Science
Author-email: AUTHOR@EMAIL.COM
License: MIT
Classifier: Development Status :: 5 - Production/Stable
Classifier: Topic :: Scientific/Engineering
Classifier: Intended Audience :: Science/Research
Classifier: Operating System :: OS Independent
Classifier: Programming Language :: Python
Classifier: Programming Language :: Python :: 3
Classifier: Programming Language :: Python :: 3.6
Classifier: Programming Language :: Python :: 3.7
Classifier: Programming Language :: Python :: 3.8
Classifier: License :: OSI Approved :: MIT License
Requires-Python: >=3.6
License-File: LICENSE.txt
Requires-Dist: pandas
Requires-Dist: regex
